hacknsun_counter/__init__.py
hacknsun_counter/counter.py
hacknsun_counter-0.1.0.dist-info/LICENSE
hacknsun_counter-0.1.0.dist-info/METADATA
hacknsun_counter-0.1.0.dist-info/WHEEL
hacknsun_counter-0.1.0.dist-info/top_level.txt
hacknsun_counter-0.1.0.dist-info/RECORD
